mistyPy/__init__.py
mistyPy-0.0.4.dist-info/METADATA
mistyPy-0.0.4.dist-info/RECORD
mistyPy-0.0.4.dist-info/WHEEL
mistyPy-0.0.4.dist-info/top_level.txt
