Metadata-Version: 2.1
Name: mistyPy
Version: 0.0.4
Summary: Python library for Misty. BETA V 0.0.4
Home-page: https://github.com/MistyCommunity/mistyPy
Author: CP Sridhar
Author-email: sridhar@mistyrobotics.com
License: UNKNOWN
Platform: UNKNOWN
Classifier: Programming Language :: Python :: 3
Classifier: License :: OSI Approved :: MIT License
Classifier: Operating System :: OS Independent
